window_hash/__init__.py
window_hash/conditions.py
window_hash-0.1.3.dist-info/LICENSE
window_hash-0.1.3.dist-info/METADATA
window_hash-0.1.3.dist-info/WHEEL
window_hash-0.1.3.dist-info/RECORD
